{"returnData": {"all_givers_anonymous": 0, "allow_comments": 0, "only_name_not_amount": 0, "currency": "USD $", "donations": [{"donation_id": 549967, "campaign_id": 49000, "donation_amount": "100.00", "donation_comment": "Thank you for your courageous stand.  We are with you!", "donation_conversion_rate": "1.000000", "donation_name": "CC", "donation_anonymous": 0, "donation_date": "6 hrs ago", "lovecount": 0, "likes": 0}, {"donation_id": 549966, "campaign_id": 49000, "donation_amount": "500.00", "donation_comment": "We love our truckers in Ottawa, standing up for freedom!  God bless you!!", "donation_conversion_rate": "1.000000", "donation_name": "D.R.J.", "donation_anonymous": 0, "donation_date": "6 hrs ago", "lovecount": 0, "likes": 0}, {"donation_id": 549965, "campaign_id": 49000, "donation_amount": "25.00", "donation_comment": "Thank you all all you are doing", "donation_conversion_rate": "1.000000", "donation_name": "Freedomkath", "donation_anonymous": 0, "donation_date": "6 hrs ago", "lovecount": 0, "likes": 0}, {"donation_id": 549964, "campaign_id": 49000, "donation_amount": "100.00", "donation_comment": "", "donation_conversion_rate": "1.000000", "donation_name": "", "donation_anonymous": 0, "donation_date": "6 hrs ago", "lovecount": 0, "likes": 0}, {"donation_id": 549963, "campaign_id": 49000, "donation_amount": "70.00", "donation_comment": "", "donation_conversion_rate": "1.000000", "donation_name": "Austin", "donation_anonymous": 0, "donation_date": "6 hrs ago", "lovecount": 0, "likes": 0}, {"donation_id": 549962, "campaign_id": 49000, "donation_amount": "100.00", "donation_comment": "", "donation_conversion_rate": "1.000000", "donation_name": "Reed Downey", "donation_anonymous": 0, "donation_date": "6 hrs ago", "lovecount": 0, "likes": 0}, {"donation_id": 549961, "campaign_id": 49000, "donation_amount": "35.00", "donation_comment": "Love you lot, stay strong, you are all helping humanity to become united", "donation_conversion_rate": "1.000000", "donation_name": "Joe", "donation_anonymous": 0, "donation_date": "6 hrs ago", "lovecount": 0, "likes": 0}, {"donation_id": 549958, "campaign_id": 49000, "donation_amount": "10.00", "donation_comment": "I lost my job because of vaccine mandate. Support you guys! Fight for freedom!", "donation_conversion_rate": "1.000000", "donation_name": "yi wang", "donation_anonymous": 0, "donation_date": "6 hrs ago", "lovecount": 0, "likes": 0}, {"donation_id": 549957, "campaign_id": 49000, "donation_amount": "50.00", "donation_comment": "Good luck. ", "donation_conversion_rate": "1.000000", "donation_name": "Nuclear Rabbit", "donation_anonymous": 0, "donation_date": "6 hrs ago", "lovecount": 0, "likes": 0}, {"donation_id": 549956, "campaign_id": 49000, "donation_amount": "100.00", "donation_comment": "Honk honk my fellow friends ", "donation_conversion_rate": "1.000000", "donation_name": "", "donation_anonymous": 1, "donation_date": "6 hrs ago", "lovecount": 0, "likes": 0}], "campaign_enabled": 1}, "code": 200}