{"returnData": {"all_givers_anonymous": 0, "allow_comments": 0, "only_name_not_amount": 0, "currency": "USD $", "donations": [{"donation_id": 575568, "campaign_id": 49000, "donation_amount": "500.00", "donation_comment": "As a dual US/Canadian citizen, I urge you to keep it up\u2026 inspire your American colleagues to follow!", "donation_conversion_rate": "1.000000", "donation_name": "", "donation_anonymous": 1, "donation_date": "24 mins ago", "lovecount": 0, "likes": 0}, {"donation_id": 575567, "campaign_id": 49000, "donation_amount": "25.00", "donation_comment": "I stand with the truckers.", "donation_conversion_rate": "1.000000", "donation_name": "", "donation_anonymous": 1, "donation_date": "24 mins ago", "lovecount": 0, "likes": 0}, {"donation_id": 575566, "campaign_id": 49000, "donation_amount": "20.00", "donation_comment": "tyrants prosper when good men do nothing", "donation_conversion_rate": "1.000000", "donation_name": "", "donation_anonymous": 1, "donation_date": "24 mins ago", "lovecount": 0, "likes": 0}, {"donation_id": 575564, "campaign_id": 49000, "donation_amount": "40.00", "donation_comment": "", "donation_conversion_rate": "1.000000", "donation_name": "", "donation_anonymous": 1, "donation_date": "25 mins ago", "lovecount": 0, "likes": 0}, {"donation_id": 575563, "campaign_id": 49000, "donation_amount": "100.00", "donation_comment": "", "donation_conversion_rate": "1.000000", "donation_name": "Andrew", "donation_anonymous": 0, "donation_date": "25 mins ago", "lovecount": 0, "likes": 0}, {"donation_id": 575562, "campaign_id": 49000, "donation_amount": "45.00", "donation_comment": "Merci pour votre action, votre courage et votre d\u00e9termination", "donation_conversion_rate": "1.000000", "donation_name": "Michele Morissette", "donation_anonymous": 0, "donation_date": "25 mins ago", "lovecount": 0, "likes": 0}, {"donation_id": 575559, "campaign_id": 49000, "donation_amount": "100.00", "donation_comment": "God please bless these truckers.", "donation_conversion_rate": "1.000000", "donation_name": "", "donation_anonymous": 1, "donation_date": "25 mins ago", "lovecount": 0, "likes": 0}, {"donation_id": 575556, "campaign_id": 49000, "donation_amount": "25.00", "donation_comment": "Thank you for raising the profile worldwide. It's time to reclaim our stolen freedoms and halt this unpleasantness.", "donation_conversion_rate": "1.000000", "donation_name": "Sue Lundie", "donation_anonymous": 0, "donation_date": "26 mins ago", "lovecount": 0, "likes": 0}, {"donation_id": 575554, "campaign_id": 49000, "donation_amount": "100.00", "donation_comment": "As a Canadian I stand with the Truckers!!\nYou are giving hope to the WORLD!\nHOLD THE LINE ~ We will win!", "donation_conversion_rate": "1.000000", "donation_name": "Heather Reid", "donation_anonymous": 0, "donation_date": "26 mins ago", "lovecount": 0, "likes": 0}, {"donation_id": 575553, "campaign_id": 49000, "donation_amount": "400.00", "donation_comment": "Thank you for supporting the freedom of the Canadian people ", "donation_conversion_rate": "1.000000", "donation_name": "Jim and Donna Crozier", "donation_anonymous": 0, "donation_date": "26 mins ago", "lovecount": 0, "likes": 0}], "campaign_enabled": 1}, "code": 200}