{"returnData": {"all_givers_anonymous": 0, "allow_comments": 0, "only_name_not_amount": 0, "currency": "USD $", "donations": [{"donation_id": 542988, "campaign_id": 49000, "donation_amount": "10.00", "donation_comment": "", "donation_conversion_rate": "1.000000", "donation_name": "", "donation_anonymous": 1, "donation_date": "10 hrs ago", "lovecount": 0, "likes": 0}, {"donation_id": 542987, "campaign_id": 49000, "donation_amount": "52.00", "donation_comment": "thank you for your courageous stand against this tyranny. We continue to support you in the ways we can, including prayers for a much better outcome than what we are presently seeing. ", "donation_conversion_rate": "1.000000", "donation_name": "", "donation_anonymous": 1, "donation_date": "10 hrs ago", "lovecount": 0, "likes": 0}, {"donation_id": 542986, "campaign_id": 49000, "donation_amount": "20.00", "donation_comment": "", "donation_conversion_rate": "1.000000", "donation_name": "Celine Berube", "donation_anonymous": 0, "donation_date": "10 hrs ago", "lovecount": 0, "likes": 0}, {"donation_id": 542985, "campaign_id": 49000, "donation_amount": "20.00", "donation_comment": "Thank you, from USA! Stay strong!", "donation_conversion_rate": "1.000000", "donation_name": "", "donation_anonymous": 1, "donation_date": "10 hrs ago", "lovecount": 0, "likes": 0}, {"donation_id": 542984, "campaign_id": 49000, "donation_amount": "20.00", "donation_comment": "", "donation_conversion_rate": "1.000000", "donation_name": "Amy Feng", "donation_anonymous": 0, "donation_date": "10 hrs ago", "lovecount": 0, "likes": 0}, {"donation_id": 542983, "campaign_id": 49000, "donation_amount": "18.00", "donation_comment": "", "donation_conversion_rate": "1.000000", "donation_name": "", "donation_anonymous": 1, "donation_date": "10 hrs ago", "lovecount": 0, "likes": 0}, {"donation_id": 542982, "campaign_id": 49000, "donation_amount": "200.00", "donation_comment": "Thank you truckers, for the love you have for your country\nand for all of humanity. We are so proud of you, and you (we)\nare sacrificing comfort in order to awaken our fellow brothers\nand sisters across all lands. Blessings always to your pure efforts.\n\n* Also thank you \"givesendgo\" for having integrity.", "donation_conversion_rate": "1.000000", "donation_name": "", "donation_anonymous": 1, "donation_date": "10 hrs ago", "lovecount": 0, "likes": 0}, {"donation_id": 542981, "campaign_id": 49000, "donation_amount": "20.00", "donation_comment": "", "donation_conversion_rate": "1.000000", "donation_name": "", "donation_anonymous": 1, "donation_date": "10 hrs ago", "lovecount": 0, "likes": 0}, {"donation_id": 542980, "campaign_id": 49000, "donation_amount": "100.00", "donation_comment": "", "donation_conversion_rate": "1.000000", "donation_name": "", "donation_anonymous": 0, "donation_date": "10 hrs ago", "lovecount": 0, "likes": 0}, {"donation_id": 542979, "campaign_id": 49000, "donation_amount": "100.00", "donation_comment": "You are doing the Lord\u2019s work. God bless you and God Bless our truckers!! ", "donation_conversion_rate": "1.000000", "donation_name": "Let Freedom Ring", "donation_anonymous": 0, "donation_date": "10 hrs ago", "lovecount": 0, "likes": 0}], "campaign_enabled": 1}, "code": 200}