{"returnData": {"all_givers_anonymous": 0, "allow_comments": 0, "only_name_not_amount": 0, "currency": "USD $", "donations": [{"donation_id": 549958, "campaign_id": 49000, "donation_amount": "10.00", "donation_comment": "I lost my job because of vaccine mandate. Support you guys! Fight for freedom!", "donation_conversion_rate": "1.000000", "donation_name": "yi wang", "donation_anonymous": 0, "donation_date": "6 hrs ago", "lovecount": 0, "likes": 0}, {"donation_id": 549957, "campaign_id": 49000, "donation_amount": "50.00", "donation_comment": "Good luck. ", "donation_conversion_rate": "1.000000", "donation_name": "Nuclear Rabbit", "donation_anonymous": 0, "donation_date": "6 hrs ago", "lovecount": 0, "likes": 0}, {"donation_id": 549956, "campaign_id": 49000, "donation_amount": "100.00", "donation_comment": "Honk honk my fellow friends ", "donation_conversion_rate": "1.000000", "donation_name": "", "donation_anonymous": 1, "donation_date": "6 hrs ago", "lovecount": 0, "likes": 0}, {"donation_id": 549955, "campaign_id": 49000, "donation_amount": "75.00", "donation_comment": "Keep on Truckn, and Keep the Faith!", "donation_conversion_rate": "1.000000", "donation_name": "Mary E Holmstrand", "donation_anonymous": 0, "donation_date": "6 hrs ago", "lovecount": 0, "likes": 0}, {"donation_id": 549954, "campaign_id": 49000, "donation_amount": "25.00", "donation_comment": "Keep up your spirit!", "donation_conversion_rate": "1.000000", "donation_name": "Leanna C", "donation_anonymous": 0, "donation_date": "6 hrs ago", "lovecount": 0, "likes": 0}, {"donation_id": 549953, "campaign_id": 49000, "donation_amount": "75.00", "donation_comment": "We stand behind you 100%", "donation_conversion_rate": "1.000000", "donation_name": "wayne hittel", "donation_anonymous": 0, "donation_date": "6 hrs ago", "lovecount": 0, "likes": 0}, {"donation_id": 549952, "campaign_id": 49000, "donation_amount": "100.00", "donation_comment": "Thank you for standing for freedom!  I\u2019m praying for you. God Bless you!  ", "donation_conversion_rate": "1.000000", "donation_name": "Janice C", "donation_anonymous": 0, "donation_date": "6 hrs ago", "lovecount": 0, "likes": 0}, {"donation_id": 549951, "campaign_id": 49000, "donation_amount": "10.00", "donation_comment": "", "donation_conversion_rate": "1.000000", "donation_name": "Tommy gobbler ", "donation_anonymous": 0, "donation_date": "6 hrs ago", "lovecount": 0, "likes": 0}, {"donation_id": 549950, "campaign_id": 49000, "donation_amount": "50.00", "donation_comment": "Honk Honk from Missouri", "donation_conversion_rate": "1.000000", "donation_name": "", "donation_anonymous": 0, "donation_date": "6 hrs ago", "lovecount": 0, "likes": 0}, {"donation_id": 549949, "campaign_id": 49000, "donation_amount": "25.00", "donation_comment": "God bless you! Honk honk!", "donation_conversion_rate": "1.000000", "donation_name": "", "donation_anonymous": 1, "donation_date": "6 hrs ago", "lovecount": 0, "likes": 0}], "campaign_enabled": 1}, "code": 200}