{"returnData": {"all_givers_anonymous": 0, "allow_comments": 0, "only_name_not_amount": 0, "currency": "USD $", "donations": [{"donation_id": 564218, "campaign_id": 49000, "donation_amount": "50.00", "donation_comment": "", "donation_conversion_rate": "1.000000", "donation_name": "RC Morley", "donation_anonymous": 0, "donation_date": "2 hrs ago", "lovecount": 0, "likes": 0}, {"donation_id": 564216, "campaign_id": 49000, "donation_amount": "40.00", "donation_comment": "Go truckers, we love you and support you until the end!!!", "donation_conversion_rate": "1.000000", "donation_name": "", "donation_anonymous": 1, "donation_date": "2 hrs ago", "lovecount": 0, "likes": 0}, {"donation_id": 564215, "campaign_id": 49000, "donation_amount": "15.00", "donation_comment": "Freedom doesn't have a price...", "donation_conversion_rate": "1.000000", "donation_name": "Ottawa", "donation_anonymous": 0, "donation_date": "2 hrs ago", "lovecount": 0, "likes": 0}, {"donation_id": 564214, "campaign_id": 49000, "donation_amount": "50.00", "donation_comment": "Thanks and God Bless you Truckers!", "donation_conversion_rate": "1.000000", "donation_name": "Mike from Cole Harbour NS", "donation_anonymous": 0, "donation_date": "2 hrs ago", "lovecount": 0, "likes": 0}, {"donation_id": 564212, "campaign_id": 49000, "donation_amount": "50.00", "donation_comment": "", "donation_conversion_rate": "1.000000", "donation_name": "", "donation_anonymous": 0, "donation_date": "2 hrs ago", "lovecount": 0, "likes": 0}, {"donation_id": 564211, "campaign_id": 49000, "donation_amount": "100.00", "donation_comment": "Keep on trucking. Canadian heroes, thank-you. ", "donation_conversion_rate": "1.000000", "donation_name": "Tara and Derrick", "donation_anonymous": 0, "donation_date": "2 hrs ago", "lovecount": 0, "likes": 0}, {"donation_id": 564210, "campaign_id": 49000, "donation_amount": "20.00", "donation_comment": "", "donation_conversion_rate": "1.000000", "donation_name": "", "donation_anonymous": 1, "donation_date": "2 hrs ago", "lovecount": 0, "likes": 0}, {"donation_id": 564209, "campaign_id": 49000, "donation_amount": "100.00", "donation_comment": "I stand with the convoy! I support the fight for our GOD-given freedoms to be returned to us! Prayers from Quebec.", "donation_conversion_rate": "1.000000", "donation_name": "", "donation_anonymous": 1, "donation_date": "2 hrs ago", "lovecount": 0, "likes": 0}, {"donation_id": 564208, "campaign_id": 49000, "donation_amount": "150.00", "donation_comment": "Thank you truckers!!", "donation_conversion_rate": "1.000000", "donation_name": "Chilly ", "donation_anonymous": 0, "donation_date": "2 hrs ago", "lovecount": 0, "likes": 0}, {"donation_id": 564207, "campaign_id": 49000, "donation_amount": "20.00", "donation_comment": "Stay strong!", "donation_conversion_rate": "1.000000", "donation_name": "Alaska is with ya", "donation_anonymous": 0, "donation_date": "2 hrs ago", "lovecount": 0, "likes": 0}], "campaign_enabled": 1}, "code": 200}