{"returnData": {"all_givers_anonymous": 0, "allow_comments": 0, "only_name_not_amount": 0, "currency": "USD $", "donations": [{"donation_id": 578035, "campaign_id": 49000, "donation_amount": "25.00", "donation_comment": "Keep up the good work Canadian Brothers and Sisters! We\u2019re with you in the USA!", "donation_conversion_rate": "1.000000", "donation_name": "US Trucker ", "donation_anonymous": 0, "donation_date": "17 hrs ago", "lovecount": 0, "likes": 0}, {"donation_id": 578034, "campaign_id": 49000, "donation_amount": "70.00", "donation_comment": "You are heros!  My husband and I stand with you as you fight for the freedoms that our Liberal government is so intent on taking away and punishing those of us who stand in opposition.  We have watched the actions of the people whom we have entrusted with our safety, behave in ways we never imagined possible in Canada. Our fathers fought a world war so we could live in Canada, strong and free. ", "donation_conversion_rate": "1.000000", "donation_name": "Lexie Brough", "donation_anonymous": 0, "donation_date": "17 hrs ago", "lovecount": 0, "likes": 0}, {"donation_id": 578033, "campaign_id": 49000, "donation_amount": "400.00", "donation_comment": "", "donation_conversion_rate": "1.000000", "donation_name": "", "donation_anonymous": 0, "donation_date": "17 hrs ago", "lovecount": 0, "likes": 0}, {"donation_id": 578032, "campaign_id": 49000, "donation_amount": "50.00", "donation_comment": "", "donation_conversion_rate": "1.000000", "donation_name": "", "donation_anonymous": 1, "donation_date": "17 hrs ago", "lovecount": 0, "likes": 0}, {"donation_id": 578031, "campaign_id": 49000, "donation_amount": "50.00", "donation_comment": "Truck yeah!", "donation_conversion_rate": "1.000000", "donation_name": "", "donation_anonymous": 0, "donation_date": "17 hrs ago", "lovecount": 0, "likes": 0}, {"donation_id": 578029, "campaign_id": 49000, "donation_amount": "8.00", "donation_comment": "I'm not telling you it's going to be easy. I am telling you it will be worth it.\nIn hoc signo vinces +", "donation_conversion_rate": "1.000000", "donation_name": "Templar", "donation_anonymous": 0, "donation_date": "17 hrs ago", "lovecount": 0, "likes": 0}, {"donation_id": 578027, "campaign_id": 49000, "donation_amount": "20.00", "donation_comment": "People deserves to claim the Freedom of their rights. I support that!", "donation_conversion_rate": "1.000000", "donation_name": "Eduardo Ramirez ", "donation_anonymous": 0, "donation_date": "17 hrs ago", "lovecount": 0, "likes": 0}, {"donation_id": 578026, "campaign_id": 49000, "donation_amount": "20.00", "donation_comment": "Sending some support from CA! Freedom!!!!!!! ", "donation_conversion_rate": "1.000000", "donation_name": "CL from Compton CA", "donation_anonymous": 0, "donation_date": "17 hrs ago", "lovecount": 0, "likes": 0}, {"donation_id": 578025, "campaign_id": 49000, "donation_amount": "100.00", "donation_comment": "God bless our truckers!! God is in control!", "donation_conversion_rate": "1.000000", "donation_name": "", "donation_anonymous": 0, "donation_date": "17 hrs ago", "lovecount": 0, "likes": 0}, {"donation_id": 578024, "campaign_id": 49000, "donation_amount": "100.00", "donation_comment": "Keep fighting the good fight. The REAL  America is with you. We'll keep you in our prayers", "donation_conversion_rate": "1.000000", "donation_name": "", "donation_anonymous": 0, "donation_date": "17 hrs ago", "lovecount": 0, "likes": 0}], "campaign_enabled": 1}, "code": 200}