{"returnData": {"all_givers_anonymous": 0, "allow_comments": 0, "only_name_not_amount": 0, "currency": "USD $", "donations": [{"donation_id": 538048, "campaign_id": 49000, "donation_amount": "100.00", "donation_comment": "", "donation_conversion_rate": "1.000000", "donation_name": "Dan and Dorothy Baker", "donation_anonymous": 0, "donation_date": "17 hrs ago", "lovecount": 0, "likes": 0}, {"donation_id": 538047, "campaign_id": 49000, "donation_amount": "50.00", "donation_comment": "Cheering you on from the US!", "donation_conversion_rate": "1.000000", "donation_name": "", "donation_anonymous": 0, "donation_date": "17 hrs ago", "lovecount": 0, "likes": 0}, {"donation_id": 538046, "campaign_id": 49000, "donation_amount": "200.00", "donation_comment": "", "donation_conversion_rate": "1.000000", "donation_name": "DJ LT", "donation_anonymous": 0, "donation_date": "17 hrs ago", "lovecount": 0, "likes": 0}, {"donation_id": 538045, "campaign_id": 49000, "donation_amount": "200.00", "donation_comment": "", "donation_conversion_rate": "1.000000", "donation_name": "", "donation_anonymous": 1, "donation_date": "17 hrs ago", "lovecount": 0, "likes": 0}, {"donation_id": 538044, "campaign_id": 49000, "donation_amount": "50.00", "donation_comment": "End the mandates now! Thank you Truckers. ", "donation_conversion_rate": "1.000000", "donation_name": "", "donation_anonymous": 1, "donation_date": "17 hrs ago", "lovecount": 0, "likes": 0}, {"donation_id": 538043, "campaign_id": 49000, "donation_amount": "100.00", "donation_comment": "", "donation_conversion_rate": "1.000000", "donation_name": "", "donation_anonymous": 0, "donation_date": "17 hrs ago", "lovecount": 0, "likes": 0}, {"donation_id": 538042, "campaign_id": 49000, "donation_amount": "25.00", "donation_comment": "", "donation_conversion_rate": "1.000000", "donation_name": "", "donation_anonymous": 1, "donation_date": "17 hrs ago", "lovecount": 0, "likes": 0}, {"donation_id": 538041, "campaign_id": 49000, "donation_amount": "45.00", "donation_comment": "Wish i could give more... but double what I gave on go f me.\nStay strong,  be safe, bless you all,  and.. honk honk", "donation_conversion_rate": "1.000000", "donation_name": "", "donation_anonymous": 0, "donation_date": "17 hrs ago", "lovecount": 0, "likes": 0}, {"donation_id": 538039, "campaign_id": 49000, "donation_amount": "25.00", "donation_comment": "Praying for you all! So proud of you.  keep up the good fight and thank you for leading the way back to freedom all over the world! ", "donation_conversion_rate": "1.000000", "donation_name": "Let\u2019s Go Brandon ", "donation_anonymous": 0, "donation_date": "17 hrs ago", "lovecount": 0, "likes": 0}, {"donation_id": 538038, "campaign_id": 49000, "donation_amount": "100.00", "donation_comment": "", "donation_conversion_rate": "1.000000", "donation_name": "", "donation_anonymous": 1, "donation_date": "17 hrs ago", "lovecount": 0, "likes": 0}], "campaign_enabled": 1}, "code": 200}