{"returnData": {"all_givers_anonymous": 0, "allow_comments": 0, "only_name_not_amount": 0, "currency": "USD $", "donations": [{"donation_id": 561508, "campaign_id": 49000, "donation_amount": "45.00", "donation_comment": "", "donation_conversion_rate": "1.000000", "donation_name": "", "donation_anonymous": 0, "donation_date": "1 hrs ago", "lovecount": 0, "likes": 0}, {"donation_id": 561507, "campaign_id": 49000, "donation_amount": "100.00", "donation_comment": "", "donation_conversion_rate": "1.000000", "donation_name": "P SIMMS", "donation_anonymous": 0, "donation_date": "1 hrs ago", "lovecount": 0, "likes": 0}, {"donation_id": 561506, "campaign_id": 49000, "donation_amount": "25.00", "donation_comment": "God bless, keep on truckin", "donation_conversion_rate": "1.000000", "donation_name": "Pappy", "donation_anonymous": 0, "donation_date": "1 hrs ago", "lovecount": 0, "likes": 0}, {"donation_id": 561505, "campaign_id": 49000, "donation_amount": "15.00", "donation_comment": "", "donation_conversion_rate": "1.000000", "donation_name": "FJB", "donation_anonymous": 0, "donation_date": "1 hrs ago", "lovecount": 0, "likes": 0}, {"donation_id": 561504, "campaign_id": 49000, "donation_amount": "100.00", "donation_comment": "Thank you truckers for taking the initiative!", "donation_conversion_rate": "1.000000", "donation_name": "Greg", "donation_anonymous": 0, "donation_date": "1 hrs ago", "lovecount": 0, "likes": 0}, {"donation_id": 561503, "campaign_id": 49000, "donation_amount": "100.00", "donation_comment": "Truckers rip & snort and knock down this tyranny!", "donation_conversion_rate": "1.000000", "donation_name": "", "donation_anonymous": 1, "donation_date": "1 hrs ago", "lovecount": 0, "likes": 0}, {"donation_id": 561502, "campaign_id": 49000, "donation_amount": "25.00", "donation_comment": "Truckers in Ottawa, the free world owes you a debt of gratitude ", "donation_conversion_rate": "1.000000", "donation_name": "Greg Purdy", "donation_anonymous": 0, "donation_date": "1 hrs ago", "lovecount": 0, "likes": 0}, {"donation_id": 561501, "campaign_id": 49000, "donation_amount": "250.00", "donation_comment": "Thank you for drawing the line and holding the line. Much love.", "donation_conversion_rate": "1.000000", "donation_name": "", "donation_anonymous": 1, "donation_date": "1 hrs ago", "lovecount": 0, "likes": 0}, {"donation_id": 561499, "campaign_id": 49000, "donation_amount": "150.00", "donation_comment": "God bless you all. I am so proud to support this just cause. There is nothing greater than our freedom. ", "donation_conversion_rate": "1.000000", "donation_name": "", "donation_anonymous": 1, "donation_date": "1 hrs ago", "lovecount": 0, "likes": 0}, {"donation_id": 561498, "campaign_id": 49000, "donation_amount": "100.00", "donation_comment": "Stay strong. Proud that you are taking action. God's blessings.", "donation_conversion_rate": "1.000000", "donation_name": "", "donation_anonymous": 1, "donation_date": "1 hrs ago", "lovecount": 0, "likes": 0}], "campaign_enabled": 1}, "code": 200}