{"returnData": {"all_givers_anonymous": 0, "allow_comments": 0, "only_name_not_amount": 0, "currency": "USD $", "donations": [{"donation_id": 562047, "campaign_id": 49000, "donation_amount": "100.00", "donation_comment": "", "donation_conversion_rate": "1.000000", "donation_name": "", "donation_anonymous": 1, "donation_date": "28 mins ago", "lovecount": 0, "likes": 0}, {"donation_id": 562046, "campaign_id": 49000, "donation_amount": "25.00", "donation_comment": "GOD BLESS YOU!!!", "donation_conversion_rate": "1.000000", "donation_name": "JOSE E ORTIZ", "donation_anonymous": 0, "donation_date": "28 mins ago", "lovecount": 0, "likes": 0}, {"donation_id": 562043, "campaign_id": 49000, "donation_amount": "50.00", "donation_comment": "Freedom is something we fight for", "donation_conversion_rate": "1.000000", "donation_name": "Anne", "donation_anonymous": 0, "donation_date": "28 mins ago", "lovecount": 0, "likes": 0}, {"donation_id": 562042, "campaign_id": 49000, "donation_amount": "5.00", "donation_comment": "As a young working American with not much to give, I see my government being just as evil as yours. Keep up the good fight neighbors! ", "donation_conversion_rate": "1.000000", "donation_name": "Giuseppe", "donation_anonymous": 0, "donation_date": "28 mins ago", "lovecount": 0, "likes": 0}, {"donation_id": 562040, "campaign_id": 49000, "donation_amount": "100.00", "donation_comment": "", "donation_conversion_rate": "1.000000", "donation_name": "", "donation_anonymous": 1, "donation_date": "28 mins ago", "lovecount": 0, "likes": 0}, {"donation_id": 562039, "campaign_id": 49000, "donation_amount": "15.00", "donation_comment": "I'm a germaphobe and even I hate mandates.", "donation_conversion_rate": "1.000000", "donation_name": "", "donation_anonymous": 1, "donation_date": "28 mins ago", "lovecount": 0, "likes": 0}, {"donation_id": 562037, "campaign_id": 49000, "donation_amount": "20.00", "donation_comment": "I immigrated to Canada because I want freedom, it's sad what's happening...", "donation_conversion_rate": "1.000000", "donation_name": "Mohamed", "donation_anonymous": 0, "donation_date": "28 mins ago", "lovecount": 0, "likes": 0}, {"donation_id": 562036, "campaign_id": 49000, "donation_amount": "50.00", "donation_comment": "Thank you, TRUCKERS!!!", "donation_conversion_rate": "1.000000", "donation_name": "", "donation_anonymous": 1, "donation_date": "29 mins ago", "lovecount": 0, "likes": 0}, {"donation_id": 562035, "campaign_id": 49000, "donation_amount": "100.00", "donation_comment": "Thank you for fighting for our freedom!", "donation_conversion_rate": "1.000000", "donation_name": "Switz", "donation_anonymous": 0, "donation_date": "29 mins ago", "lovecount": 0, "likes": 0}, {"donation_id": 562034, "campaign_id": 49000, "donation_amount": "100.00", "donation_comment": "", "donation_conversion_rate": "1.000000", "donation_name": "", "donation_anonymous": 1, "donation_date": "29 mins ago", "lovecount": 0, "likes": 0}], "campaign_enabled": 1}, "code": 200}