{"returnData": {"all_givers_anonymous": 0, "allow_comments": 0, "only_name_not_amount": 0, "currency": "USD $", "donations": [{"donation_id": 568468, "campaign_id": 49000, "donation_amount": "50.00", "donation_comment": "Praying for you all! Stay peaceful, stay loving, hold the line. \u2764\ufe0f", "donation_conversion_rate": "1.000000", "donation_name": "", "donation_anonymous": 0, "donation_date": "14 hrs ago", "lovecount": 0, "likes": 0}, {"donation_id": 568467, "campaign_id": 49000, "donation_amount": "25.00", "donation_comment": "Thank you for standing strong and defending our Canadian constitutional rights!", "donation_conversion_rate": "1.000000", "donation_name": "Gerry Born", "donation_anonymous": 0, "donation_date": "14 hrs ago", "lovecount": 0, "likes": 0}, {"donation_id": 568466, "campaign_id": 49000, "donation_amount": "20.00", "donation_comment": "Truckers are heroes!!", "donation_conversion_rate": "1.000000", "donation_name": "AE", "donation_anonymous": 0, "donation_date": "14 hrs ago", "lovecount": 0, "likes": 0}, {"donation_id": 568465, "campaign_id": 49000, "donation_amount": "75.00", "donation_comment": "Donation to support the Canadian Truckers and their Freedom cause.  Godspeed.", "donation_conversion_rate": "1.000000", "donation_name": "Refugees from New Jersey", "donation_anonymous": 0, "donation_date": "14 hrs ago", "lovecount": 0, "likes": 0}, {"donation_id": 568463, "campaign_id": 49000, "donation_amount": "45.00", "donation_comment": "Thank you for all that you are doing for Canadians !! ", "donation_conversion_rate": "1.000000", "donation_name": "janice", "donation_anonymous": 0, "donation_date": "14 hrs ago", "lovecount": 0, "likes": 0}, {"donation_id": 568462, "campaign_id": 49000, "donation_amount": "100.00", "donation_comment": "Please keep up the good fight and thank you ", "donation_conversion_rate": "1.000000", "donation_name": "", "donation_anonymous": 1, "donation_date": "14 hrs ago", "lovecount": 0, "likes": 0}, {"donation_id": 568461, "campaign_id": 49000, "donation_amount": "100.00", "donation_comment": "", "donation_conversion_rate": "1.000000", "donation_name": "", "donation_anonymous": 1, "donation_date": "14 hrs ago", "lovecount": 0, "likes": 0}, {"donation_id": 568460, "campaign_id": 49000, "donation_amount": "25.00", "donation_comment": "", "donation_conversion_rate": "1.000000", "donation_name": "", "donation_anonymous": 1, "donation_date": "14 hrs ago", "lovecount": 0, "likes": 0}, {"donation_id": 568459, "campaign_id": 49000, "donation_amount": "30.00", "donation_comment": "", "donation_conversion_rate": "1.000000", "donation_name": "", "donation_anonymous": 0, "donation_date": "14 hrs ago", "lovecount": 0, "likes": 0}, {"donation_id": 568457, "campaign_id": 49000, "donation_amount": "20.00", "donation_comment": "We support you.  Thank you for fighting for our FREEDOM!!", "donation_conversion_rate": "1.000000", "donation_name": "Ontario Canada", "donation_anonymous": 0, "donation_date": "14 hrs ago", "lovecount": 0, "likes": 0}], "campaign_enabled": 1}, "code": 200}