{"returnData": {"all_givers_anonymous": 0, "allow_comments": 0, "only_name_not_amount": 0, "currency": "USD $", "donations": [{"donation_id": 554838, "campaign_id": 49000, "donation_amount": "25.00", "donation_comment": "Keep fighting for freedom ", "donation_conversion_rate": "1.000000", "donation_name": "", "donation_anonymous": 1, "donation_date": "3 hrs ago", "lovecount": 0, "likes": 0}, {"donation_id": 554836, "campaign_id": 49000, "donation_amount": "50.00", "donation_comment": "", "donation_conversion_rate": "1.000000", "donation_name": "John", "donation_anonymous": 0, "donation_date": "3 hrs ago", "lovecount": 0, "likes": 0}, {"donation_id": 554835, "campaign_id": 49000, "donation_amount": "20.00", "donation_comment": "", "donation_conversion_rate": "1.000000", "donation_name": "", "donation_anonymous": 1, "donation_date": "3 hrs ago", "lovecount": 0, "likes": 0}, {"donation_id": 554832, "campaign_id": 49000, "donation_amount": "100.00", "donation_comment": "This it\u2019s not only a fight for freedom it had now become a fight of good vs evil! God bless you! I will continue working and sponsoring you guys so we can all enjoy the victory!", "donation_conversion_rate": "1.000000", "donation_name": "", "donation_anonymous": 1, "donation_date": "3 hrs ago", "lovecount": 0, "likes": 0}, {"donation_id": 554831, "campaign_id": 49000, "donation_amount": "5.00", "donation_comment": "Standing in solidarity across the border! ", "donation_conversion_rate": "1.000000", "donation_name": "Come arrest us Trudeau ", "donation_anonymous": 0, "donation_date": "3 hrs ago", "lovecount": 0, "likes": 0}, {"donation_id": 554830, "campaign_id": 49000, "donation_amount": "50.00", "donation_comment": "We pray that God's will shall be achieved in this Convoy. We are proud to be Canadians supporting brave individuals who stand up for our God-given freedom!", "donation_conversion_rate": "1.000000", "donation_name": "Dan and  Cecile Missionaries for Christ", "donation_anonymous": 0, "donation_date": "3 hrs ago", "lovecount": 0, "likes": 0}, {"donation_id": 554829, "campaign_id": 49000, "donation_amount": "100.00", "donation_comment": "Freedom Convoy 2022 has our full support and prayers.  We owe all of you a massive debt of gratitude!\n\n\n\n\n\n\n", "donation_conversion_rate": "1.000000", "donation_name": "Josie", "donation_anonymous": 1, "donation_date": "3 hrs ago", "lovecount": 0, "likes": 0}, {"donation_id": 554828, "campaign_id": 49000, "donation_amount": "30.00", "donation_comment": "Our governments are out of control.Thank you for taking a stand.Dont give up till they remove the mandates.", "donation_conversion_rate": "1.000000", "donation_name": "Anonymous", "donation_anonymous": 0, "donation_date": "3 hrs ago", "lovecount": 0, "likes": 0}, {"donation_id": 554827, "campaign_id": 49000, "donation_amount": "25.00", "donation_comment": "I Thank all you Truckers & supporters for Standing up.  We love you", "donation_conversion_rate": "1.000000", "donation_name": "Rick L", "donation_anonymous": 0, "donation_date": "3 hrs ago", "lovecount": 0, "likes": 0}, {"donation_id": 554825, "campaign_id": 49000, "donation_amount": "25.00", "donation_comment": "Never give up!!! Thank you for your sacrifice\u2764\ufe0f\ud83c\uddfa\ud83c\uddf8\ud83c\uddfa\ud83c\uddf8\u2764\ufe0f", "donation_conversion_rate": "1.000000", "donation_name": "Mainers are with you", "donation_anonymous": 0, "donation_date": "3 hrs ago", "lovecount": 0, "likes": 0}], "campaign_enabled": 1}, "code": 200}