{"returnData": {"all_givers_anonymous": 0, "allow_comments": 0, "only_name_not_amount": 0, "currency": "USD $", "donations": [{"donation_id": 557827, "campaign_id": 49000, "donation_amount": "100.00", "donation_comment": "", "donation_conversion_rate": "1.000000", "donation_name": "Ca ", "donation_anonymous": 0, "donation_date": "10 hrs ago", "lovecount": 0, "likes": 0}, {"donation_id": 557826, "campaign_id": 49000, "donation_amount": "40.00", "donation_comment": "", "donation_conversion_rate": "1.000000", "donation_name": "Ron B", "donation_anonymous": 0, "donation_date": "10 hrs ago", "lovecount": 0, "likes": 0}, {"donation_id": 557825, "campaign_id": 49000, "donation_amount": "200.00", "donation_comment": "", "donation_conversion_rate": "1.000000", "donation_name": "Greg and  Kathleen Wiltsey", "donation_anonymous": 0, "donation_date": "10 hrs ago", "lovecount": 0, "likes": 0}, {"donation_id": 557823, "campaign_id": 49000, "donation_amount": "200.00", "donation_comment": "Thank you so much to all the organizers of this Freedom Convoy! Bigger thanks to all the truckers and their families who are standing up for all of us! We stand with you! ", "donation_conversion_rate": "1.000000", "donation_name": "Judy Graves", "donation_anonymous": 0, "donation_date": "10 hrs ago", "lovecount": 0, "likes": 0}, {"donation_id": 557821, "campaign_id": 49000, "donation_amount": "50.00", "donation_comment": "TRUCKERS ARE SAVING THE WORLD! WE STAND WITH YOU!!! Cause...\"we got a great big convoy Rockin' through the night Yeah, we got a great big convoy Ain't she a beautiful sight?\n", "donation_conversion_rate": "1.000000", "donation_name": "", "donation_anonymous": 1, "donation_date": "10 hrs ago", "lovecount": 0, "likes": 0}, {"donation_id": 557820, "campaign_id": 49000, "donation_amount": "20.00", "donation_comment": "Thank you for you bravery, Truckers.", "donation_conversion_rate": "1.000000", "donation_name": "", "donation_anonymous": 1, "donation_date": "10 hrs ago", "lovecount": 0, "likes": 0}, {"donation_id": 557819, "campaign_id": 49000, "donation_amount": "50.00", "donation_comment": "Thank You Truckers.", "donation_conversion_rate": "1.000000", "donation_name": "", "donation_anonymous": 1, "donation_date": "10 hrs ago", "lovecount": 0, "likes": 0}, {"donation_id": 557818, "campaign_id": 49000, "donation_amount": "50.00", "donation_comment": "", "donation_conversion_rate": "1.000000", "donation_name": "", "donation_anonymous": 0, "donation_date": "10 hrs ago", "lovecount": 0, "likes": 0}, {"donation_id": 557816, "campaign_id": 49000, "donation_amount": "20.00", "donation_comment": "", "donation_conversion_rate": "1.000000", "donation_name": "Lets Go Brandon", "donation_anonymous": 0, "donation_date": "10 hrs ago", "lovecount": 0, "likes": 0}, {"donation_id": 557815, "campaign_id": 49000, "donation_amount": "100.00", "donation_comment": "Thank you", "donation_conversion_rate": "1.000000", "donation_name": "", "donation_anonymous": 1, "donation_date": "10 hrs ago", "lovecount": 0, "likes": 0}], "campaign_enabled": 1}, "code": 200}