{"returnData": {"all_givers_anonymous": 0, "allow_comments": 0, "only_name_not_amount": 0, "currency": "USD $", "donations": [{"donation_id": 558918, "campaign_id": 49000, "donation_amount": "10.00", "donation_comment": "Honk! Honk! You have inspired so many of us with your stand for Freedom! Thank You. ", "donation_conversion_rate": "1.000000", "donation_name": "", "donation_anonymous": 1, "donation_date": "9 hrs ago", "lovecount": 0, "likes": 0}, {"donation_id": 558917, "campaign_id": 49000, "donation_amount": "40.00", "donation_comment": "You truckers might save the world !", "donation_conversion_rate": "1.000000", "donation_name": "", "donation_anonymous": 1, "donation_date": "9 hrs ago", "lovecount": 0, "likes": 0}, {"donation_id": 558916, "campaign_id": 49000, "donation_amount": "100.00", "donation_comment": "", "donation_conversion_rate": "1.000000", "donation_name": "Eric Lobban", "donation_anonymous": 0, "donation_date": "9 hrs ago", "lovecount": 0, "likes": 0}, {"donation_id": 558915, "campaign_id": 49000, "donation_amount": "100.00", "donation_comment": "", "donation_conversion_rate": "1.000000", "donation_name": "", "donation_anonymous": 1, "donation_date": "9 hrs ago", "lovecount": 0, "likes": 0}, {"donation_id": 558914, "campaign_id": 49000, "donation_amount": "30.00", "donation_comment": "Honk!", "donation_conversion_rate": "1.000000", "donation_name": "Big Scene", "donation_anonymous": 0, "donation_date": "9 hrs ago", "lovecount": 0, "likes": 0}, {"donation_id": 558913, "campaign_id": 49000, "donation_amount": "50.00", "donation_comment": "We ain\u2019t going to take it!", "donation_conversion_rate": "1.000000", "donation_name": "Bella ", "donation_anonymous": 0, "donation_date": "9 hrs ago", "lovecount": 0, "likes": 0}, {"donation_id": 558912, "campaign_id": 49000, "donation_amount": "40.00", "donation_comment": "2000 years ago we were practicing Pagan religions and Christ gave us the power to break free.   Today they are beginning to show their faces once more.  The spirits infest their followers and have them do their bidding.  The white lodge Freemasons are everywhere and are running the world.", "donation_conversion_rate": "1.000000", "donation_name": "", "donation_anonymous": 0, "donation_date": "9 hrs ago", "lovecount": 0, "likes": 0}, {"donation_id": 558909, "campaign_id": 49000, "donation_amount": "25.00", "donation_comment": "", "donation_conversion_rate": "1.000000", "donation_name": "", "donation_anonymous": 1, "donation_date": "9 hrs ago", "lovecount": 0, "likes": 0}, {"donation_id": 558907, "campaign_id": 49000, "donation_amount": "5.00", "donation_comment": " it Trudeau. Let\u2019s go Truckers!!! \nShowing support from Alaska", "donation_conversion_rate": "1.000000", "donation_name": "Derek seims", "donation_anonymous": 0, "donation_date": "9 hrs ago", "lovecount": 0, "likes": 0}, {"donation_id": 558906, "campaign_id": 49000, "donation_amount": "25.00", "donation_comment": "You make me proud to have you as my northern neighbor.", "donation_conversion_rate": "1.000000", "donation_name": "", "donation_anonymous": 1, "donation_date": "9 hrs ago", "lovecount": 0, "likes": 0}], "campaign_enabled": 1}, "code": 200}