{"returnData": {"all_givers_anonymous": 0, "allow_comments": 0, "only_name_not_amount": 0, "currency": "USD $", "donations": [{"donation_id": 581918, "campaign_id": 49000, "donation_amount": "20.00", "donation_comment": "God Bless the America\u2019s", "donation_conversion_rate": "1.000000", "donation_name": "", "donation_anonymous": 0, "donation_date": "11 hrs ago", "lovecount": 0, "likes": 0}, {"donation_id": 581915, "campaign_id": 49000, "donation_amount": "30.00", "donation_comment": "Please keep up the good fight", "donation_conversion_rate": "1.000000", "donation_name": "", "donation_anonymous": 0, "donation_date": "11 hrs ago", "lovecount": 0, "likes": 0}, {"donation_id": 581914, "campaign_id": 49000, "donation_amount": "20.00", "donation_comment": "God bless the truckies and Canada for standing up. It's the US's turn next.", "donation_conversion_rate": "1.000000", "donation_name": "", "donation_anonymous": 0, "donation_date": "11 hrs ago", "lovecount": 0, "likes": 0}, {"donation_id": 581913, "campaign_id": 49000, "donation_amount": "50.00", "donation_comment": "Hold the line stay safe please god bless. ", "donation_conversion_rate": "1.000000", "donation_name": "KZED", "donation_anonymous": 0, "donation_date": "11 hrs ago", "lovecount": 0, "likes": 0}, {"donation_id": 581912, "campaign_id": 49000, "donation_amount": "25.00", "donation_comment": "Stay Strong", "donation_conversion_rate": "1.000000", "donation_name": "Zebradog", "donation_anonymous": 0, "donation_date": "11 hrs ago", "lovecount": 0, "likes": 0}, {"donation_id": 581910, "campaign_id": 49000, "donation_amount": "20.00", "donation_comment": "TRUCKERS! You are saving Canada and it\u2019s people. Thank you from the bottom of my heart for giving people like me, a voice for freedom. We love you and stand with you always!", "donation_conversion_rate": "1.000000", "donation_name": "", "donation_anonymous": 0, "donation_date": "11 hrs ago", "lovecount": 0, "likes": 0}, {"donation_id": 581907, "campaign_id": 49000, "donation_amount": "100.00", "donation_comment": "So grateful for each of you. Stay peaceful and strong! \ud83d\ude4f", "donation_conversion_rate": "1.000000", "donation_name": "Paul and Linda Kappus", "donation_anonymous": 0, "donation_date": "11 hrs ago", "lovecount": 0, "likes": 0}, {"donation_id": 581906, "campaign_id": 49000, "donation_amount": "100.00", "donation_comment": "Do what is right. Not what is easy.", "donation_conversion_rate": "1.000000", "donation_name": "CanadAmerica ", "donation_anonymous": 0, "donation_date": "11 hrs ago", "lovecount": 0, "likes": 0}, {"donation_id": 581903, "campaign_id": 49000, "donation_amount": "24.00", "donation_comment": "My brothers and sisters in Canada, I am so proud of you! You are in my prayers. Stand Strong! You have been prophesied over and you will win this battle! Let the Lord lead you to Victory! There are more with you than against you. Love from a fellow sister in the U.S. WE ARE WITH YOU!", "donation_conversion_rate": "1.000000", "donation_name": "", "donation_anonymous": 1, "donation_date": "11 hrs ago", "lovecount": 0, "likes": 0}, {"donation_id": 581900, "campaign_id": 49000, "donation_amount": "100.00", "donation_comment": "", "donation_conversion_rate": "1.000000", "donation_name": "", "donation_anonymous": 0, "donation_date": "11 hrs ago", "lovecount": 0, "likes": 0}], "campaign_enabled": 1}, "code": 200}