{"returnData": {"all_givers_anonymous": 0, "allow_comments": 0, "only_name_not_amount": 0, "currency": "USD $", "donations": [{"donation_id": 560788, "campaign_id": 49000, "donation_amount": "25.00", "donation_comment": "", "donation_conversion_rate": "1.000000", "donation_name": "", "donation_anonymous": 1, "donation_date": "2 hrs ago", "lovecount": 0, "likes": 0}, {"donation_id": 560787, "campaign_id": 49000, "donation_amount": "50.00", "donation_comment": "Next up: U.S./Mexico border", "donation_conversion_rate": "1.000000", "donation_name": "FKtheGovt", "donation_anonymous": 0, "donation_date": "2 hrs ago", "lovecount": 0, "likes": 0}, {"donation_id": 560786, "campaign_id": 49000, "donation_amount": "50.00", "donation_comment": "My thoughts and prayers are with you all. Thank you for showing the world how we feel and doing it in a PEACEFUL manner. ", "donation_conversion_rate": "1.000000", "donation_name": "", "donation_anonymous": 1, "donation_date": "2 hrs ago", "lovecount": 0, "likes": 0}, {"donation_id": 560785, "campaign_id": 49000, "donation_amount": "25.00", "donation_comment": "", "donation_conversion_rate": "1.000000", "donation_name": "JesusIsWithYou", "donation_anonymous": 0, "donation_date": "2 hrs ago", "lovecount": 0, "likes": 0}, {"donation_id": 560784, "campaign_id": 49000, "donation_amount": "400.00", "donation_comment": "", "donation_conversion_rate": "1.000000", "donation_name": "", "donation_anonymous": 1, "donation_date": "2 hrs ago", "lovecount": 0, "likes": 0}, {"donation_id": 560783, "campaign_id": 49000, "donation_amount": "30.00", "donation_comment": "", "donation_conversion_rate": "1.000000", "donation_name": "", "donation_anonymous": 1, "donation_date": "2 hrs ago", "lovecount": 0, "likes": 0}, {"donation_id": 560782, "campaign_id": 49000, "donation_amount": "20.00", "donation_comment": "", "donation_conversion_rate": "1.000000", "donation_name": "", "donation_anonymous": 0, "donation_date": "2 hrs ago", "lovecount": 0, "likes": 0}, {"donation_id": 560780, "campaign_id": 49000, "donation_amount": "20.00", "donation_comment": "Thank You!!  Hold the Line!!!  The world is watching and WEV are with YOU!!!!!  GOD BLESS!!!!", "donation_conversion_rate": "1.000000", "donation_name": "Greta Ford", "donation_anonymous": 0, "donation_date": "2 hrs ago", "lovecount": 0, "likes": 0}, {"donation_id": 560778, "campaign_id": 49000, "donation_amount": "20.00", "donation_comment": "Bravo to all of the truckers! ", "donation_conversion_rate": "1.000000", "donation_name": "Gerald Talton", "donation_anonymous": 0, "donation_date": "2 hrs ago", "lovecount": 0, "likes": 0}, {"donation_id": 560776, "campaign_id": 49000, "donation_amount": "50.00", "donation_comment": "disgusted by our Country's leaders and the minions who serve them. ", "donation_conversion_rate": "1.000000", "donation_name": "Ryan Grant", "donation_anonymous": 0, "donation_date": "2 hrs ago", "lovecount": 0, "likes": 0}], "campaign_enabled": 1}, "code": 200}