{"returnData": {"all_givers_anonymous": 0, "allow_comments": 0, "only_name_not_amount": 0, "currency": "USD $", "donations": [{"donation_id": 559517, "campaign_id": 49000, "donation_amount": "20.00", "donation_comment": "", "donation_conversion_rate": "1.000000", "donation_name": "", "donation_anonymous": 1, "donation_date": "8 hrs ago", "lovecount": 0, "likes": 0}, {"donation_id": 559516, "campaign_id": 49000, "donation_amount": "100.00", "donation_comment": "Thank you for all that you are doing!!\u2764\u2764you give us hope!!\u2764", "donation_conversion_rate": "1.000000", "donation_name": "SA McLean", "donation_anonymous": 0, "donation_date": "8 hrs ago", "lovecount": 0, "likes": 0}, {"donation_id": 559515, "campaign_id": 49000, "donation_amount": "63.00", "donation_comment": "Go Truckers!", "donation_conversion_rate": "1.000000", "donation_name": "", "donation_anonymous": 0, "donation_date": "8 hrs ago", "lovecount": 0, "likes": 0}, {"donation_id": 559514, "campaign_id": 49000, "donation_amount": "5.00", "donation_comment": "Thanks!", "donation_conversion_rate": "1.000000", "donation_name": "A Ham Radio operator", "donation_anonymous": 0, "donation_date": "8 hrs ago", "lovecount": 0, "likes": 0}, {"donation_id": 559512, "campaign_id": 49000, "donation_amount": "25.00", "donation_comment": "Thank you Canadians!", "donation_conversion_rate": "1.000000", "donation_name": "", "donation_anonymous": 1, "donation_date": "8 hrs ago", "lovecount": 0, "likes": 0}, {"donation_id": 559511, "campaign_id": 49000, "donation_amount": "30.00", "donation_comment": "Loving everything you people are doing.  Please keep going as you are inspiring many across the planet to do the same.  Whatever we have to do to get our freedoms back, then we must, even if that means unseating our governments, who seem  bent on driving us all into Communism and a One World Order!  They can shove that up their collective arses!  Love to you all from Tasmania.", "donation_conversion_rate": "1.000000", "donation_name": "The Thiebauds", "donation_anonymous": 0, "donation_date": "8 hrs ago", "lovecount": 0, "likes": 0}, {"donation_id": 559510, "campaign_id": 49000, "donation_amount": "20.00", "donation_comment": "See it through.", "donation_conversion_rate": "1.000000", "donation_name": "", "donation_anonymous": 1, "donation_date": "8 hrs ago", "lovecount": 0, "likes": 0}, {"donation_id": 559509, "campaign_id": 49000, "donation_amount": "100.00", "donation_comment": "THANK YOU TRUCKERS and brave citizens standing up and supporting freedom around the world!", "donation_conversion_rate": "1.000000", "donation_name": "", "donation_anonymous": 1, "donation_date": "8 hrs ago", "lovecount": 0, "likes": 0}, {"donation_id": 559507, "campaign_id": 49000, "donation_amount": "100.00", "donation_comment": "", "donation_conversion_rate": "1.000000", "donation_name": "", "donation_anonymous": 1, "donation_date": "8 hrs ago", "lovecount": 0, "likes": 0}, {"donation_id": 559506, "campaign_id": 49000, "donation_amount": "8.00", "donation_comment": "", "donation_conversion_rate": "1.000000", "donation_name": "FREEDOMNOW", "donation_anonymous": 0, "donation_date": "8 hrs ago", "lovecount": 0, "likes": 0}], "campaign_enabled": 1}, "code": 200}