[
  {
    "member":"Abigail Spanberger",
    "party":"Democratic",
    "views":174336
  },
  {
    "member":"Adam Kinzinger",
    "party":"Republican",
    "views":1431625
  },
  {
    "member":"Adam Schiff",
    "party":"Democratic",
    "views":422809
  },
  {
    "member":"Adam Smith ",
    "party":"Democratic",
    "views":1697
  },
  {
    "member":"Adrian Smith ",
    "party":"Republican",
    "views":25441
  },
  {
    "member":"Adriano Espaillat",
    "party":"Democratic",
    "views":76098
  },
  {
    "member":"Al Green ",
    "party":"Democratic",
    "views":103531
  },
  {
    "member":"Al Lawson",
    "party":"Democratic",
    "views":39248
  },
  {
    "member":"Alan Lowenthal",
    "party":"Democratic",
    "views":29470
  },
  {
    "member":"Albio Sires",
    "party":"Democratic",
    "views":33022
  },
  {
    "member":"Alex Mooney",
    "party":"Republican",
    "views":87416
  },
  {
    "member":"Alexandria Ocasio-Cortez",
    "party":"Democratic",
    "views":3918370
  },
  {
    "member":"Alma Adams",
    "party":"Democratic",
    "views":45035
  },
  {
    "member":"Ami Bera",
    "party":"Democratic",
    "views":62904
  },
  {
    "member":"Andrew Clyde",
    "party":"Republican",
    "views":269023
  },
  {
    "member":"Andrew Garbarino",
    "party":"Republican",
    "views":65755
  },
  {
    "member":"Andy Barr ",
    "party":"Republican",
    "views":43031
  },
  {
    "member":"Andy Biggs",
    "party":"Republican",
    "views":177121
  },
  {
    "member":"Andy Harris ",
    "party":"Republican",
    "views":136378
  },
  {
    "member":"Andy Kim ",
    "party":"Democratic",
    "views":219323
  },
  {
    "member":"Andy Levin",
    "party":"Democratic",
    "views":62729
  },
  {
    "member":"Angie Craig",
    "party":"Democratic",
    "views":76692
  },
  {
    "member":"Ann McLane Kuster",
    "party":"Democratic",
    "views":40514
  },
  {
    "member":"Ann Wagner",
    "party":"Republican",
    "views":75404
  },
  {
    "member":"Anna Eshoo",
    "party":"Democratic",
    "views":82003
  },
  {
    "member":"Anthony G. Brown",
    "party":"Democratic",
    "views":73760
  },
  {
    "member":"Anthony Gonzalez ",
    "party":"Republican",
    "views":314733
  },
  {
    "member":"Antonio Delgado ",
    "party":"Democratic",
    "views":75503
  },
  {
    "member":"Ashley Hinson",
    "party":"Republican",
    "views":115651
  },
  {
    "member":"August Pfluger",
    "party":"Republican",
    "views":47209
  },
  {
    "member":"Austin Scott ",
    "party":"Republican",
    "views":26347
  },
  {
    "member":"Ayanna Pressley",
    "party":"Democratic",
    "views":464714
  },
  {
    "member":"Barbara Lee",
    "party":"Democratic",
    "views":243552
  },
  {
    "member":"Barry Moore ",
    "party":"Republican",
    "views":54265
  },
  {
    "member":"Ben Cline",
    "party":"Republican",
    "views":38287
  },
  {
    "member":"Bennie Thompson",
    "party":"Democratic",
    "views":177482
  },
  {
    "member":"Beth Van Duyne",
    "party":"Republican",
    "views":153934
  },
  {
    "member":"Betty McCollum",
    "party":"Democratic",
    "views":50952
  },
  {
    "member":"Bill Foster ",
    "party":"Democratic",
    "views":36671
  },
  {
    "member":"Bill Huizenga",
    "party":"Republican",
    "views":58463
  },
  {
    "member":"Bill Johnson ",
    "party":"Republican",
    "views":31683
  },
  {
    "member":"Bill Keating ",
    "party":"Democratic",
    "views":34646
  },
  {
    "member":"Bill Pascrell",
    "party":"Democratic",
    "views":55121
  },
  {
    "member":"Bill Posey",
    "party":"Republican",
    "views":43033
  },
  {
    "member":"Billy Long",
    "party":"Republican",
    "views":53301
  },
  {
    "member":"Blaine Luetkemeyer",
    "party":"Republican",
    "views":31287
  },
  {
    "member":"Blake Moore",
    "party":"Republican",
    "views":58140
  },
  {
    "member":"Bob Gibbs",
    "party":"Republican",
    "views":26884
  },
  {
    "member":"Bob Good",
    "party":"Republican",
    "views":76548
  },
  {
    "member":"Bob Latta",
    "party":"Republican",
    "views":21713
  },
  {
    "member":"Bobby Rush",
    "party":"Democratic",
    "views":201812
  },
  {
    "member":"Bobby Scott ",
    "party":"Democratic",
    "views":46808
  },
  {
    "member":"Bonnie Watson Coleman",
    "party":"Democratic",
    "views":80814
  },
  {
    "member":"Brad Schneider",
    "party":"Democratic",
    "views":62164
  },
  {
    "member":"Brad Sherman",
    "party":"Democratic",
    "views":78918
  },
  {
    "member":"Brad Wenstrup",
    "party":"Republican",
    "views":41198
  },
  {
    "member":"Brenda Lawrence",
    "party":"Democratic",
    "views":37190
  },
  {
    "member":"Brendan Boyle",
    "party":"Democratic",
    "views":93775
  },
  {
    "member":"Brett Guthrie",
    "party":"Republican",
    "views":20262
  },
  {
    "member":"Brian Babin",
    "party":"Republican",
    "views":64028
  },
  {
    "member":"Brian Fitzpatrick ",
    "party":"Republican",
    "views":109194
  },
  {
    "member":"Brian Higgins",
    "party":"Democratic",
    "views":40992
  },
  {
    "member":"Brian Mast",
    "party":"Republican",
    "views":194248
  },
  {
    "member":"Bruce Westerman",
    "party":"Republican",
    "views":26599
  },
  {
    "member":"Bryan Steil",
    "party":"Republican",
    "views":56813
  },
  {
    "member":"Buddy Carter",
    "party":"Republican",
    "views":56542
  },
  {
    "member":"Burgess Owens",
    "party":"Republican",
    "views":336303
  },
  {
    "member":"Byron Donalds",
    "party":"Republican",
    "views":271157
  },
  {
    "member":"Carol Miller ",
    "party":"Republican",
    "views":41448
  },
  {
    "member":"Carolyn Bourdeaux",
    "party":"Democratic",
    "views":90365
  },
  {
    "member":"Carolyn Maloney",
    "party":"Democratic",
    "views":167781
  },
  {
    "member":"Cathy McMorris Rodgers",
    "party":"Republican",
    "views":115215
  },
  {
    "member":"Charlie Crist",
    "party":"Democratic",
    "views":471773
  },
  {
    "member":"Chellie Pingree",
    "party":"Democratic",
    "views":44135
  },
  {
    "member":"Cheri Bustos",
    "party":"Democratic",
    "views":86441
  },
  {
    "member":"Chip Roy",
    "party":"Republican",
    "views":225151
  },
  {
    "member":"Chris Jacobs ",
    "party":"Republican",
    "views":59580
  },
  {
    "member":"Chris Pappas ",
    "party":"Democratic",
    "views":77277
  },
  {
    "member":"Chris Smith ",
    "party":"Republican",
    "views":84631
  },
  {
    "member":"Chris Stewart ",
    "party":"Republican",
    "views":43627
  },
  {
    "member":"Chrissy Houlahan",
    "party":"Democratic",
    "views":89465
  },
  {
    "member":"Chuck Fleischmann",
    "party":"Republican",
    "views":30654
  },
  {
    "member":"Cindy Axne",
    "party":"Democratic",
    "views":86261
  },
  {
    "member":"Claudia Tenney",
    "party":"Republican",
    "views":163705
  },
  {
    "member":"Clay Higgins",
    "party":"Republican",
    "views":117662
  },
  {
    "member":"Cliff Bentz",
    "party":"Republican",
    "views":51460
  },
  {
    "member":"Colin Allred",
    "party":"Democratic",
    "views":234378
  },
  {
    "member":"Conor Lamb",
    "party":"Democratic",
    "views":309018
  },
  {
    "member":"Cori Bush",
    "party":"Democratic",
    "views":741520
  },
  {
    "member":"Dan Bishop",
    "party":"Republican",
    "views":46828
  },
  {
    "member":"Dan Kildee",
    "party":"Democratic",
    "views":67140
  },
  {
    "member":"Dan Meuser",
    "party":"Republican",
    "views":34410
  },
  {
    "member":"Dan Newhouse",
    "party":"Republican",
    "views":84336
  },
  {
    "member":"Daniel Webster ",
    "party":"Republican",
    "views":52902
  },
  {
    "member":"Danny K. Davis",
    "party":"Democratic",
    "views":59754
  },
  {
    "member":"Darin LaHood",
    "party":"Republican",
    "views":47978
  },
  {
    "member":"Darrell Issa",
    "party":"Republican",
    "views":220999
  },
  {
    "member":"Darren Soto",
    "party":"Democratic",
    "views":40889
  },
  {
    "member":"David Cicilline",
    "party":"Democratic",
    "views":252404
  },
  {
    "member":"David Joyce ",
    "party":"Republican",
    "views":30837
  },
  {
    "member":"David Kustoff",
    "party":"Republican",
    "views":27727
  },
  {
    "member":"David McKinley",
    "party":"Republican",
    "views":52605
  },
  {
    "member":"David Price ",
    "party":"Democratic",
    "views":51804
  },
  {
    "member":"David Rouzer",
    "party":"Republican",
    "views":27741
  },
  {
    "member":"David Schweikert",
    "party":"Republican",
    "views":61590
  },
  {
    "member":"David Scott ",
    "party":"Democratic",
    "views":65425
  },
  {
    "member":"David Trone",
    "party":"Democratic",
    "views":61624
  },
  {
    "member":"David Valadao",
    "party":"Republican",
    "views":127639
  },
  {
    "member":"Dean Phillips",
    "party":"Democratic",
    "views":91834
  },
  {
    "member":"Debbie Dingell",
    "party":"Democratic",
    "views":160126
  },
  {
    "member":"Debbie Lesko",
    "party":"Republican",
    "views":66426
  },
  {
    "member":"Debbie Wasserman Schultz",
    "party":"Democratic",
    "views":225230
  },
  {
    "member":"Deborah K. Ross",
    "party":"Democratic",
    "views":66351
  },
  {
    "member":"Derek Kilmer",
    "party":"Democratic",
    "views":39353
  },
  {
    "member":"Devin Nunes",
    "party":"Republican",
    "views":336581
  },
  {
    "member":"Diana DeGette",
    "party":"Democratic",
    "views":99986
  },
  {
    "member":"Diana Harshbarger",
    "party":"Republican",
    "views":51846
  },
  {
    "member":"Dina Titus",
    "party":"Democratic",
    "views":55775
  },
  {
    "member":"Don Bacon",
    "party":"Republican",
    "views":48068
  },
  {
    "member":"Don Beyer",
    "party":"Democratic",
    "views":76959
  },
  {
    "member":"Don Young",
    "party":"Republican",
    "views":247633
  },
  {
    "member":"Donald McEachin",
    "party":"Democratic",
    "views":25959
  },
  {
    "member":"Donald Norcross",
    "party":"Democratic",
    "views":38696
  },
  {
    "member":"Donald Payne Jr.",
    "party":"Democratic",
    "views":29985
  },
  {
    "member":"Doug LaMalfa",
    "party":"Republican",
    "views":77376
  },
  {
    "member":"Doug Lamborn",
    "party":"Republican",
    "views":45834
  },
  {
    "member":"Drew Ferguson ",
    "party":"Republican",
    "views":37609
  },
  {
    "member":"Dusty Johnson",
    "party":"Republican",
    "views":51941
  },
  {
    "member":"Dutch Ruppersberger",
    "party":"Democratic",
    "views":34196
  },
  {
    "member":"Dwight Evans ",
    "party":"Democratic",
    "views":38032
  },
  {
    "member":"Earl Blumenauer",
    "party":"Democratic",
    "views":45393
  },
  {
    "member":"Ed Case",
    "party":"Democratic",
    "views":91371
  },
  {
    "member":"Ed Perlmutter",
    "party":"Democratic",
    "views":36309
  },
  {
    "member":"Eddie Bernice Johnson",
    "party":"Democratic",
    "views":71489
  },
  {
    "member":"Elaine Luria",
    "party":"Democratic",
    "views":118504
  },
  {
    "member":"Elissa Slotkin",
    "party":"Democratic",
    "views":153062
  },
  {
    "member":"Emanuel Cleaver",
    "party":"Democratic",
    "views":126860
  },
  {
    "member":"Eric Swalwell",
    "party":"Democratic",
    "views":543674
  },
  {
    "member":"Filemon Vela Jr.",
    "party":"Democratic",
    "views":47291
  },
  {
    "member":"Frank J. Mrvan",
    "party":"Democratic",
    "views":45002
  },
  {
    "member":"Frank Lucas ",
    "party":"Republican",
    "views":25337
  },
  {
    "member":"Frank Pallone",
    "party":"Democratic",
    "views":45496
  },
  {
    "member":"Fred Keller ",
    "party":"Republican",
    "views":27593
  },
  {
    "member":"Fred Upton",
    "party":"Republican",
    "views":166290
  },
  {
    "member":"Frederica Wilson",
    "party":"Democratic",
    "views":69716
  },
  {
    "member":"French Hill ",
    "party":"Republican",
    "views":38951
  },
  {
    "member":"G. K. Butterfield",
    "party":"Democratic",
    "views":88653
  },
  {
    "member":"Garret Graves",
    "party":"Republican",
    "views":37560
  },
  {
    "member":"Gary Palmer ",
    "party":"Republican",
    "views":35586
  },
  {
    "member":"Gerry Connolly",
    "party":"Democratic",
    "views":58950
  },
  {
    "member":"Glenn Grothman",
    "party":"Republican",
    "views":47702
  },
  {
    "member":"Glenn Thompson ",
    "party":"Republican",
    "views":32953
  },
  {
    "member":"Grace Meng",
    "party":"Democratic",
    "views":119739
  },
  {
    "member":"Grace Napolitano",
    "party":"Democratic",
    "views":30759
  },
  {
    "member":"Greg Murphy ",
    "party":"Republican",
    "views":39124
  },
  {
    "member":"Greg Pence",
    "party":"Republican",
    "views":212769
  },
  {
    "member":"Greg Stanton",
    "party":"Democratic",
    "views":59168
  },
  {
    "member":"Greg Steube",
    "party":"Republican",
    "views":121500
  },
  {
    "member":"Gregory Meeks",
    "party":"Democratic",
    "views":78144
  },
  {
    "member":"Gus Bilirakis",
    "party":"Republican",
    "views":36326
  },
  {
    "member":"Guy Reschenthaler",
    "party":"Republican",
    "views":54491
  },
  {
    "member":"Gwen Moore",
    "party":"Democratic",
    "views":40458
  },
  {
    "member":"Hakeem Jeffries",
    "party":"Democratic",
    "views":260613
  },
  {
    "member":"Hal Rogers",
    "party":"Republican",
    "views":48803
  },
  {
    "member":"Haley Stevens",
    "party":"Democratic",
    "views":61354
  },
  {
    "member":"Hank Johnson",
    "party":"Democratic",
    "views":194547
  },
  {
    "member":"Henry Cuellar",
    "party":"Democratic",
    "views":92016
  },
  {
    "member":"Ilhan Omar",
    "party":"Democratic",
    "views":1315468
  },
  {
    "member":"Jack Bergman",
    "party":"Republican",
    "views":51607
  },
  {
    "member":"Jackie Speier",
    "party":"Democratic",
    "views":355745
  },
  {
    "member":"Jahana Hayes",
    "party":"Democratic",
    "views":53441
  },
  {
    "member":"Jaime Herrera Beutler",
    "party":"Republican",
    "views":347626
  },
  {
    "member":"Jake Auchincloss",
    "party":"Democratic",
    "views":230944
  },
  {
    "member":"Jake Ellzey",
    "party":"Republican",
    "views":120014
  },
  {
    "member":"Jake LaTurner",
    "party":"Republican",
    "views":55125
  },
  {
    "member":"Jamaal Bowman",
    "party":"Democratic",
    "views":243927
  },
  {
    "member":"James Comer ",
    "party":"Republican",
    "views":44138
  },
  {
    "member":"James Langevin",
    "party":"Democratic",
    "views":47943
  },
  {
    "member":"Jamie Raskin",
    "party":"Democratic",
    "views":1493522
  },
  {
    "member":"Jan Schakowsky",
    "party":"Democratic",
    "views":58039
  },
  {
    "member":"Jared Golden",
    "party":"Democratic",
    "views":149056
  },
  {
    "member":"Jared Huffman",
    "party":"Democratic",
    "views":69890
  },
  {
    "member":"Jason Smith ",
    "party":"Republican",
    "views":59676
  },
  {
    "member":"Jay Obernolte",
    "party":"Republican",
    "views":63887
  },
  {
    "member":"Jeff Duncan ",
    "party":"Republican",
    "views":46146
  },
  {
    "member":"Jeff Fortenberry",
    "party":"Republican",
    "views":61042
  },
  {
    "member":"Jennifer Wexton",
    "party":"Democratic",
    "views":69118
  },
  {
    "member":"Jerry Carl",
    "party":"Republican",
    "views":40620
  },
  {
    "member":"Jerry McNerney",
    "party":"Democratic",
    "views":34689
  },
  {
    "member":"Jerry Nadler",
    "party":"Democratic",
    "views":219919
  },
  {
    "member":"Jim Baird ",
    "party":"Republican",
    "views":5589
  },
  {
    "member":"Jim Banks",
    "party":"Republican",
    "views":136692
  },
  {
    "member":"Jim Clyburn",
    "party":"Democratic",
    "views":346825
  },
  {
    "member":"Jim Cooper",
    "party":"Democratic",
    "views":92330
  },
  {
    "member":"Jim Costa",
    "party":"Democratic",
    "views":49377
  },
  {
    "member":"Jim Hagedorn",
    "party":"Republican",
    "views":62168
  },
  {
    "member":"Jim Himes",
    "party":"Democratic",
    "views":77729
  },
  {
    "member":"Jim Jordan ",
    "party":"Republican",
    "views":982582
  },
  {
    "member":"Jim McGovern ",
    "party":"Democratic",
    "views":94173
  },
  {
    "member":"Jimmy Gomez",
    "party":"Democratic",
    "views":65190
  },
  {
    "member":"Jimmy Panetta",
    "party":"Democratic",
    "views":67958
  },
  {
    "member":"Joaquin Castro",
    "party":"Democratic",
    "views":271573
  },
  {
    "member":"Jodey Arrington",
    "party":"Republican",
    "views":29320
  },
  {
    "member":"Jody Hice",
    "party":"Republican",
    "views":88412
  },
  {
    "member":"Joe Courtney ",
    "party":"Democratic",
    "views":26044
  },
  {
    "member":"Joe Neguse",
    "party":"Democratic",
    "views":643566
  },
  {
    "member":"Joe Wilson ",
    "party":"Republican",
    "views":89509
  },
  {
    "member":"John B. Larson",
    "party":"Democratic",
    "views":31915
  },
  {
    "member":"John Carter ",
    "party":"Republican",
    "views":25260
  },
  {
    "member":"John Curtis ",
    "party":"Republican",
    "views":37369
  },
  {
    "member":"John Joyce ",
    "party":"Republican",
    "views":26551
  },
  {
    "member":"John Katko",
    "party":"Republican",
    "views":147570
  },
  {
    "member":"John Moolenaar",
    "party":"Republican",
    "views":20965
  },
  {
    "member":"John Rose ",
    "party":"Republican",
    "views":22529
  },
  {
    "member":"John Rutherford ",
    "party":"Republican",
    "views":28987
  },
  {
    "member":"John Sarbanes",
    "party":"Democratic",
    "views":67217
  },
  {
    "member":"John Yarmuth",
    "party":"Democratic",
    "views":90963
  },
  {
    "member":"Joseph Morelle",
    "party":"Democratic",
    "views":30103
  },
  {
    "member":"Josh Gottheimer",
    "party":"Democratic",
    "views":110681
  },
  {
    "member":"Josh Harder",
    "party":"Democratic",
    "views":50465
  },
  {
    "member":"Joyce Beatty",
    "party":"Democratic",
    "views":94061
  },
  {
    "member":"Juan Vargas",
    "party":"Democratic",
    "views":35558
  },
  {
    "member":"Judy Chu",
    "party":"Democratic",
    "views":97354
  },
  {
    "member":"Julia Brownley",
    "party":"Democratic",
    "views":31180
  },
  {
    "member":"Kai Kahele",
    "party":"Democratic",
    "views":243824
  },
  {
    "member":"Karen Bass",
    "party":"Democratic",
    "views":133605
  },
  {
    "member":"Kathleen Rice",
    "party":"Democratic",
    "views":73171
  },
  {
    "member":"Kathy Castor",
    "party":"Democratic",
    "views":47471
  },
  {
    "member":"Kathy Manning",
    "party":"Democratic",
    "views":57636
  },
  {
    "member":"Katie Porter",
    "party":"Democratic",
    "views":404612
  },
  {
    "member":"Kay Granger",
    "party":"Republican",
    "views":50258
  },
  {
    "member":"Kelly Armstrong",
    "party":"Republican",
    "views":43147
  },
  {
    "member":"Ken Calvert",
    "party":"Republican",
    "views":42443
  },
  {
    "member":"Kevin Brady",
    "party":"Republican",
    "views":78712
  },
  {
    "member":"Kevin Hern",
    "party":"Republican",
    "views":33840
  },
  {
    "member":"Kevin McCarthy ",
    "party":"Republican",
    "views":1248842
  },
  {
    "member":"Kim Schrier",
    "party":"Democratic",
    "views":45085
  },
  {
    "member":"Kurt Schrader",
    "party":"Democratic",
    "views":81953
  },
  {
    "member":"Kweisi Mfume",
    "party":"Democratic",
    "views":109522
  },
  {
    "member":"Lance Gooden",
    "party":"Republican",
    "views":36535
  },
  {
    "member":"Larry Bucshon",
    "party":"Republican",
    "views":22131
  },
  {
    "member":"Lauren Boebert",
    "party":"Republican",
    "views":2840268
  },
  {
    "member":"Lauren Underwood",
    "party":"Democratic",
    "views":120991
  },
  {
    "member":"Lee Zeldin",
    "party":"Republican",
    "views":221783
  },
  {
    "member":"Lisa Blunt Rochester",
    "party":"Democratic",
    "views":86554
  },
  {
    "member":"Lisa McClain",
    "party":"Republican",
    "views":75293
  },
  {
    "member":"Liz Cheney",
    "party":"Republican",
    "views":3658324
  },
  {
    "member":"Lizzie Pannill Fletcher",
    "party":"Democratic",
    "views":6100
  },
  {
    "member":"Lloyd Doggett",
    "party":"Democratic",
    "views":60947
  },
  {
    "member":"Lloyd Smucker",
    "party":"Republican",
    "views":32103
  },
  {
    "member":"Lois Frankel",
    "party":"Democratic",
    "views":65272
  },
  {
    "member":"Lori Trahan",
    "party":"Democratic",
    "views":71745
  },
  {
    "member":"Lou Correa",
    "party":"Democratic",
    "views":71945
  },
  {
    "member":"Louie Gohmert",
    "party":"Republican",
    "views":257543
  },
  {
    "member":"Lucille Roybal-Allard",
    "party":"Democratic",
    "views":32465
  },
  {
    "member":"Lucy McBath",
    "party":"Democratic",
    "views":196307
  },
  {
    "member":"Madeleine Dean",
    "party":"Democratic",
    "views":229827
  },
  {
    "member":"Madison Cawthorn",
    "party":"Republican",
    "views":2340889
  },
  {
    "member":"Marc Veasey",
    "party":"Democratic",
    "views":33014
  },
  {
    "member":"Marcy Kaptur",
    "party":"Democratic",
    "views":70570
  },
  {
    "member":"Maria Elvira Salazar",
    "party":"Republican",
    "views":223528
  },
  {
    "member":"Mariannette Miller-Meeks",
    "party":"Republican",
    "views":126597
  },
  {
    "member":"Marie Newman",
    "party":"Democratic",
    "views":173074
  },
  {
    "member":"Marilyn Strickland",
    "party":"Democratic",
    "views":122000
  },
  {
    "member":"Marjorie Taylor Greene",
    "party":"Republican",
    "views":4875798
  },
  {
    "member":"Mark DeSaulnier",
    "party":"Democratic",
    "views":41988
  },
  {
    "member":"Mark E. Green",
    "party":"Republican",
    "views":69491
  },
  {
    "member":"Mark Pocan",
    "party":"Democratic",
    "views":90894
  },
  {
    "member":"Mark Takano",
    "party":"Democratic",
    "views":63489
  },
  {
    "member":"Markwayne Mullin",
    "party":"Republican",
    "views":204478
  },
  {
    "member":"Mary Gay Scanlon",
    "party":"Democratic",
    "views":58873
  },
  {
    "member":"Mary Miller ",
    "party":"Republican",
    "views":218174
  },
  {
    "member":"Matt Cartwright",
    "party":"Democratic",
    "views":53973
  },
  {
    "member":"Matt Gaetz",
    "party":"Republican",
    "views":4010896
  },
  {
    "member":"Matt Rosendale",
    "party":"Republican",
    "views":99025
  },
  {
    "member":"Maxine Waters",
    "party":"Democratic",
    "views":714824
  },
  {
    "member":"Melanie Stansbury",
    "party":"Democratic",
    "views":152412
  },
  {
    "member":"Michael C. Burgess",
    "party":"Republican",
    "views":35300
  },
  {
    "member":"Michael Cloud",
    "party":"Republican",
    "views":31687
  },
  {
    "member":"Michael F. Doyle",
    "party":"Democratic",
    "views":11589
  },
  {
    "member":"Michael Guest ",
    "party":"Republican",
    "views":26370
  },
  {
    "member":"Michael McCaul",
    "party":"Republican",
    "views":96823
  },
  {
    "member":"Michael Waltz",
    "party":"Republican",
    "views":169984
  },
  {
    "member":"Michelle Fischbach",
    "party":"Republican",
    "views":81475
  },
  {
    "member":"Michelle Steel",
    "party":"Republican",
    "views":177735
  },
  {
    "member":"Mike Bost",
    "party":"Republican",
    "views":34686
  },
  {
    "member":"Mike Carey ",
    "party":"Republican",
    "views":27305
  },
  {
    "member":"Mike Gallagher ",
    "party":"Republican",
    "views":185797
  },
  {
    "member":"Mike Garcia ",
    "party":"Republican",
    "views":104442
  },
  {
    "member":"Mike Johnson ",
    "party":"Republican",
    "views":58488
  },
  {
    "member":"Mike Kelly ",
    "party":"Republican",
    "views":53223
  },
  {
    "member":"Mike Levin",
    "party":"Democratic",
    "views":59223
  },
  {
    "member":"Mike Quigley ",
    "party":"Democratic",
    "views":42332
  },
  {
    "member":"Mike Rogers ",
    "party":"Republican",
    "views":45927
  },
  {
    "member":"Mike Simpson",
    "party":"Republican",
    "views":37708
  },
  {
    "member":"Mike Thompson ",
    "party":"Democratic",
    "views":40455
  },
  {
    "member":"Mike Turner",
    "party":"Republican",
    "views":54050
  },
  {
    "member":"Mikie Sherrill",
    "party":"Democratic",
    "views":205906
  },
  {
    "member":"Mo Brooks",
    "party":"Republican",
    "views":366717
  },
  {
    "member":"Mondaire Jones",
    "party":"Democratic",
    "views":176804
  },
  {
    "member":"Morgan Griffith",
    "party":"Republican",
    "views":42584
  },
  {
    "member":"Nancy Mace",
    "party":"Republican",
    "views":794255
  },
  {
    "member":"Neal Dunn",
    "party":"Republican",
    "views":29185
  },
  {
    "member":"Nicole Malliotakis",
    "party":"Republican",
    "views":258393
  },
  {
    "member":"Nikema Williams",
    "party":"Democratic",
    "views":129810
  },
  {
    "member":"Norma Torres",
    "party":"Democratic",
    "views":59927
  },
  {
    "member":"Pat Fallon",
    "party":"Republican",
    "views":63030
  },
  {
    "member":"Patrick McHenry",
    "party":"Republican",
    "views":49118
  },
  {
    "member":"Paul Gosar",
    "party":"Republican",
    "views":774234
  },
  {
    "member":"Paul Tonko",
    "party":"Democratic",
    "views":32143
  },
  {
    "member":"Pete Aguilar",
    "party":"Democratic",
    "views":62236
  },
  {
    "member":"Pete Sessions",
    "party":"Republican",
    "views":105191
  },
  {
    "member":"Pete Stauber",
    "party":"Republican",
    "views":38956
  },
  {
    "member":"Peter DeFazio",
    "party":"Democratic",
    "views":72258
  },
  {
    "member":"Peter Meijer",
    "party":"Republican",
    "views":458742
  },
  {
    "member":"Peter Welch",
    "party":"Democratic",
    "views":84156
  },
  {
    "member":"Pramila Jayapal",
    "party":"Democratic",
    "views":485376
  },
  {
    "member":"Ralph Norman",
    "party":"Republican",
    "views":48980
  },
  {
    "member":"Randy Feenstra",
    "party":"Republican",
    "views":84862
  },
  {
    "member":"Randy Weber",
    "party":"Republican",
    "views":31269
  },
  {
    "member":"Rashida Tlaib",
    "party":"Democratic",
    "views":614483
  },
  {
    "member":"Raul Ruiz ",
    "party":"Democratic",
    "views":56739
  },
  {
    "member":"Richard Hudson ",
    "party":"Republican",
    "views":25966
  },
  {
    "member":"Richard Neal",
    "party":"Democratic",
    "views":69166
  },
  {
    "member":"Rick Crawford ",
    "party":"Republican",
    "views":28265
  },
  {
    "member":"Rick Larsen",
    "party":"Democratic",
    "views":29139
  },
  {
    "member":"Rick W. Allen",
    "party":"Republican",
    "views":24761
  },
  {
    "member":"Ritchie Torres",
    "party":"Democratic",
    "views":286006
  },
  {
    "member":"Ro Khanna",
    "party":"Democratic",
    "views":303248
  },
  {
    "member":"Rob Wittman",
    "party":"Republican",
    "views":49338
  },
  {
    "member":"Robert Aderholt",
    "party":"Republican",
    "views":47403
  },
  {
    "member":"Robin Kelly",
    "party":"Democratic",
    "views":48067
  },
  {
    "member":"Rodney Davis ",
    "party":"Republican",
    "views":77297
  },
  {
    "member":"Roger Williams ",
    "party":"Republican",
    "views":31737
  },
  {
    "member":"Ron Estes",
    "party":"Republican",
    "views":32847
  },
  {
    "member":"Ron Kind",
    "party":"Democratic",
    "views":82690
  },
  {
    "member":"Ronny Jackson",
    "party":"Republican",
    "views":452136
  },
  {
    "member":"Rosa DeLauro",
    "party":"Democratic",
    "views":177617
  },
  {
    "member":"Ruben Gallego",
    "party":"Democratic",
    "views":186408
  },
  {
    "member":"Russ Fulcher",
    "party":"Republican",
    "views":43112
  },
  {
    "member":"Salud Carbajal",
    "party":"Democratic",
    "views":46341
  },
  {
    "member":"Sam Graves",
    "party":"Republican",
    "views":35333
  },
  {
    "member":"Sanford Bishop",
    "party":"Democratic",
    "views":43936
  },
  {
    "member":"Sara Jacobs",
    "party":"Democratic",
    "views":189833
  },
  {
    "member":"Scott DesJarlais",
    "party":"Republican",
    "views":59586
  },
  {
    "member":"Scott Franklin ",
    "party":"Republican",
    "views":37255
  },
  {
    "member":"Scott L. Fitzgerald",
    "party":"Republican",
    "views":43492
  },
  {
    "member":"Scott Perry ",
    "party":"Republican",
    "views":116453
  },
  {
    "member":"Scott Peters ",
    "party":"Democratic",
    "views":46048
  },
  {
    "member":"Sean Casten",
    "party":"Democratic",
    "views":61618
  },
  {
    "member":"Sean Patrick Maloney",
    "party":"Democratic",
    "views":174242
  },
  {
    "member":"Seth Moulton",
    "party":"Democratic",
    "views":166192
  },
  {
    "member":"Sharice Davids",
    "party":"Democratic",
    "views":164310
  },
  {
    "member":"Sheila Jackson Lee",
    "party":"Democratic",
    "views":192782
  },
  {
    "member":"Shontel Brown",
    "party":"Democratic",
    "views":79605
  },
  {
    "member":"Steny Hoyer",
    "party":"Democratic",
    "views":568310
  },
  {
    "member":"Stephanie Bice",
    "party":"Republican",
    "views":91182
  },
  {
    "member":"Stephanie Murphy",
    "party":"Democratic",
    "views":221586
  },
  {
    "member":"Stephen F. Lynch",
    "party":"Democratic",
    "views":50485
  },
  {
    "member":"Steve Chabot",
    "party":"Republican",
    "views":46375
  },
  {
    "member":"Steve Cohen ",
    "party":"Democratic",
    "views":25523
  },
  {
    "member":"Steve Scalise",
    "party":"Republican",
    "views":317832
  },
  {
    "member":"Steven Horsford",
    "party":"Democratic",
    "views":47362
  },
  {
    "member":"Steven Palazzo",
    "party":"Republican",
    "views":35239
  },
  {
    "member":"Susan Wild",
    "party":"Democratic",
    "views":101663
  },
  {
    "member":"Susie Lee",
    "party":"Democratic",
    "views":48176
  },
  {
    "member":"Suzan DelBene",
    "party":"Democratic",
    "views":54260
  },
  {
    "member":"Sylvia Garcia",
    "party":"Democratic",
    "views":47238
  },
  {
    "member":"Ted Budd",
    "party":"Republican",
    "views":112013
  },
  {
    "member":"Ted Deutch",
    "party":"Democratic",
    "views":75820
  },
  {
    "member":"Ted Lieu",
    "party":"Democratic",
    "views":356462
  },
  {
    "member":"Teresa Leger Fernandez",
    "party":"Democratic",
    "views":61351
  },
  {
    "member":"Terri Sewell",
    "party":"Democratic",
    "views":91401
  },
  {
    "member":"Thomas Massie",
    "party":"Republican",
    "views":221834
  },
  {
    "member":"Tim Burchett",
    "party":"Republican",
    "views":46424
  },
  {
    "member":"Tim Ryan ",
    "party":"Democratic",
    "views":293289
  },
  {
    "member":"Tim Walberg",
    "party":"Republican",
    "views":29924
  },
  {
    "member":"Tom Cole",
    "party":"Republican",
    "views":83267
  },
  {
    "member":"Tom Emmer",
    "party":"Republican",
    "views":68625
  },
  {
    "member":"Tom Reed ",
    "party":"Republican",
    "views":132595
  },
  {
    "member":"Tom Rice",
    "party":"Republican",
    "views":113248
  },
  {
    "member":"Tom Tiffany",
    "party":"Republican",
    "views":50217
  },
  {
    "member":"Tony Gonzales",
    "party":"Republican",
    "views":91407
  },
  {
    "member":"Tracey Mann",
    "party":"Republican",
    "views":39937
  },
  {
    "member":"Trent Kelly",
    "party":"Republican",
    "views":37938
  },
  {
    "member":"Trey Hollingsworth",
    "party":"Republican",
    "views":34821
  },
  {
    "member":"Troy Balderson",
    "party":"Republican",
    "views":27290
  },
  {
    "member":"Troy Carter ",
    "party":"Democratic",
    "views":114059
  },
  {
    "member":"Troy Nehls",
    "party":"Republican",
    "views":66331
  },
  {
    "member":"Val Demings",
    "party":"Democratic",
    "views":304739
  },
  {
    "member":"Van Taylor",
    "party":"Republican",
    "views":48200
  },
  {
    "member":"Vern Buchanan",
    "party":"Republican",
    "views":48105
  },
  {
    "member":"Veronica Escobar",
    "party":"Democratic",
    "views":81418
  },
  {
    "member":"Vicente Gonzalez ",
    "party":"Democratic",
    "views":59497
  },
  {
    "member":"Vicky Hartzler",
    "party":"Republican",
    "views":56778
  },
  {
    "member":"Victoria Spartz",
    "party":"Republican",
    "views":137295
  },
  {
    "member":"Virginia Foxx",
    "party":"Republican",
    "views":77913
  },
  {
    "member":"Warren Davidson",
    "party":"Republican",
    "views":56301
  },
  {
    "member":"William Timmons",
    "party":"Republican",
    "views":46238
  },
  {
    "member":"Young Kim",
    "party":"Republican",
    "views":238134
  },
  {
    "member":"Yvette Clarke",
    "party":"Democratic",
    "views":52593
  },
  {
    "member":"Yvette Herrell",
    "party":"Republican",
    "views":118679
  },
  {
    "member":"Zoe Lofgren",
    "party":"Democratic",
    "views":125174
  },
  {
    "member":"none",
    "party":"Vacant",
    "views":172
  }
]